gopos/__init__.py
gopos/client.py
gopos/models/__init__.py
gopos/models/address.py
gopos/models/health.py
gopos/models/timezone.py
gopos-1.0.0.dist-info/LICENSE
gopos-1.0.0.dist-info/WHEEL
gopos-1.0.0.dist-info/METADATA
gopos-1.0.0.dist-info/RECORD
